filamentlib/BiotSavart.py
filamentlib/ClosedDerivatives.py
filamentlib/EvolveKappaBinormal.py
filamentlib/EvolveRegularBiotSavart.py
filamentlib/KappaBinormal.py
filamentlib/RegularBiotSavart.py
filamentlib/__init__.py
filamentlib-0.1.2.dist-info/LICENSE
filamentlib-0.1.2.dist-info/METADATA
filamentlib-0.1.2.dist-info/WHEEL
filamentlib-0.1.2.dist-info/top_level.txt
filamentlib-0.1.2.dist-info/RECORD
