Metadata-Version: 2.1
Name: filamentlib
Version: 0.1.2
Summary: Simulate the evolution of any given vortex filament over time
Author: Daniel Krawciw
Author-email: dkrawciw@mines.edu
License: MIT
Requires-Python: >=3.10
License-File: LICENSE
Requires-Dist: numpy >=1.26
Requires-Dist: scipy >=1.13.0
